romnn_sphinx_press_theme/__init__.py
romnn_sphinx_press_theme/domainindex.html
romnn_sphinx_press_theme/genindex.html
romnn_sphinx_press_theme/layout.html
romnn_sphinx_press_theme/page.html
romnn_sphinx_press_theme/search.html
romnn_sphinx_press_theme/theme.conf
romnn_sphinx_press_theme/static/romnn_sphinx_press_theme.css
romnn_sphinx_press_theme/util/bodyheader.html
romnn_sphinx_press_theme/util/extlinks.html
romnn_sphinx_press_theme/util/footer.html
romnn_sphinx_press_theme/util/linktags.html
romnn_sphinx_press_theme/util/navbar.html
romnn_sphinx_press_theme/util/navlinks.html
romnn_sphinx_press_theme/util/pagenav.html
romnn_sphinx_press_theme/util/searchbox.html
romnn_sphinx_press_theme/util/sidetoc.html
romnnn_sphinx_press_theme-0.5.11.dist-info/AUTHORS.rst
romnnn_sphinx_press_theme-0.5.11.dist-info/METADATA
romnnn_sphinx_press_theme-0.5.11.dist-info/WHEEL
romnnn_sphinx_press_theme-0.5.11.dist-info/entry_points.txt
romnnn_sphinx_press_theme-0.5.11.dist-info/top_level.txt
romnnn_sphinx_press_theme-0.5.11.dist-info/RECORD
