Metadata-Version: 2.1
Name: romnnn-sphinx-press-theme
Version: 0.5.11
Summary: A Sphinx-doc theme based on Vuepress
Home-page: https://github.com/romnn/sphinx_press_theme
Author: romnn
License: MIT
Keywords: sphinx,doc,theme,vue.js
Platform: UNKNOWN
Classifier: Framework :: Sphinx
Classifier: Framework :: Sphinx :: Theme
Classifier: Development Status :: 4 - Beta
Classifier: License :: OSI Approved :: MIT License
Classifier: Environment :: Console
Classifier: Environment :: Web Environment
Classifier: Intended Audience :: Developers
Classifier: Programming Language :: Python :: 3
Classifier: Programming Language :: Python :: 3.5
Classifier: Programming Language :: Python :: 3.6
Classifier: Programming Language :: Python :: 3.7
Classifier: Operating System :: OS Independent
Classifier: Topic :: Documentation
Classifier: Topic :: Software Development :: Documentation
Requires-Dist: sphinx (>=2.0.0)
Requires-Dist: sphinxemoji
